fml/__init__.py
fml/__main__.py
fml/ai_service.py
fml/gather_system_info.py
fml/output_formatter.py
fml/schemas.py
fml/ai_providers/__init__.py
fml/ai_providers/gemini_service.py
fml/ai_providers/models.py
fml/prompts/gemini_system_prompt.py
fml_ai-0.6.0.dist-info/METADATA
fml_ai-0.6.0.dist-info/WHEEL
fml_ai-0.6.0.dist-info/entry_points.txt
fml_ai-0.6.0.dist-info/licenses/LICENSE
fml_ai-0.6.0.dist-info/RECORD
