Metadata-Version: 2.4
Name: fml-ai
Version: 0.6.0
Summary: FML (forgot my line) terminal AI to help you remember cli commands and flags
Project-URL: Homepage, https://github.com/YourAverageMo/fml
License-File: LICENSE
Requires-Python: >=3.12
Requires-Dist: colorama>=0.4.6
Requires-Dist: google-genai>=1.18.0
Requires-Dist: pyperclip>=1.9.0
